pydantic_avro/__init__.py
pydantic_avro/__main__.py
pydantic_avro/base.py
pydantic_avro/from_avro/__init__.py
pydantic_avro/from_avro/avro_to_pydantic.py
pydantic_avro/from_avro/class_registery.py
pydantic_avro/from_avro/types.py
pydantic_avro/py.typed
pydantic_avro/to_avro/__init__.py
pydantic_avro/to_avro/base.py
pydantic_avro/to_avro/config.py
pydantic_avro/to_avro/types.py
pydantic_avro-0.9.3.dist-info/entry_points.txt
pydantic_avro-0.9.3.dist-info/LICENSE
pydantic_avro-0.9.3.dist-info/WHEEL
pydantic_avro-0.9.3.dist-info/METADATA
pydantic_avro-0.9.3.dist-info/RECORD
