Metadata-Version: 2.1
Name: pydantic-avro
Version: 0.9.3
Summary: Converting pydantic classes to avro schemas
Home-page: https://github.com/godatadriven/pydantic-avro
License: MIT
Keywords: pydantic,avro
Author: Peter van 't Hof'
Author-email: peter.vanthof@godatadriven.com
Requires-Python: >=3.8.1,<4.0
Classifier: License :: OSI Approved :: MIT License
Classifier: Programming Language :: Python :: 3
Classifier: Programming Language :: Python :: 3.9
Classifier: Programming Language :: Python :: 3.10
Classifier: Programming Language :: Python :: 3.11
Requires-Dist: pydantic (>=1.4,<3.0)
Project-URL: Repository, https://github.com/godatadriven/pydantic-avro
